tomato_psutil/__init__.py
tomato_psutil-2.1.0.dist-info/licenses/LICENSE
tomato_psutil-2.1.0.dist-info/METADATA
tomato_psutil-2.1.0.dist-info/WHEEL
tomato_psutil-2.1.0.dist-info/top_level.txt
tomato_psutil-2.1.0.dist-info/RECORD
